trick17/__about__.py
trick17/__init__.py
trick17/daemon.py
trick17/journal.py
trick17/py.typed
trick17/util.py
trick17-0.0.4.dist-info/METADATA
trick17-0.0.4.dist-info/WHEEL
trick17-0.0.4.dist-info/licenses/LICENSE.txt
trick17-0.0.4.dist-info/RECORD
