Metadata-Version: 2.3
Name: trick17
Version: 0.0.4
Summary: Systemd utility functions in pure python
Project-URL: Documentation, https://github.com/miccoli/trick17#readme
Project-URL: Issues, https://github.com/miccoli/trick17/issues
Project-URL: Source, https://github.com/miccoli/trick17
Author-email: Stefano Miccoli <stefano.miccoli@polimi.it>
License-Expression: MIT
License-File: LICENSE.txt
Keywords: systemd
Classifier: Development Status :: 2 - Pre-Alpha
Classifier: Intended Audience :: Developers
Classifier: Operating System :: POSIX :: Linux
Classifier: Programming Language :: Python
Classifier: Programming Language :: Python :: 3.10
Classifier: Programming Language :: Python :: 3.11
Classifier: Programming Language :: Python :: 3.12
Classifier: Programming Language :: Python :: Implementation :: CPython
Requires-Python: >=3.10
